Dragonflyz/__init__.py
Dragonflyz/disk_monitor.py
Dragonflyz/energy.py
Dragonflyz/gantt.py
Dragonflyz/sensor_info.py
Dragonflyz/system_utils.py
Dragonflyz-2.0.5.dist-info/LICENSE
Dragonflyz-2.0.5.dist-info/METADATA
Dragonflyz-2.0.5.dist-info/WHEEL
Dragonflyz-2.0.5.dist-info/top_level.txt
Dragonflyz-2.0.5.dist-info/RECORD
