Metadata-Version: 2.1
Name: Dragonflyz
Version: 2.0.5
Summary: Package for Code Analysis across your scripts
Home-page: https://github.com/jacob-h-barrow/Dragonflyz
Author: Jacob H Barrow
Author-email: jacob.h.barrow@gmail.com
License: MIT
Platform: UNKNOWN
Classifier: License :: OSI Approved :: MIT License
Classifier: Programming Language :: Python
Classifier: Programming Language :: Python :: 3
License-File: LICENSE
Requires-Dist: dataclasses
Requires-Dist: matplotlib
Requires-Dist: panel
